{"query":{"count":88,"created":"2013-05-09T06:45:40Z","lang":"en-US","diagnostics":{"publiclyCallable":"true","redirect":{"from":"http://datatables.org/alltables.env","status":"301","content":"http://www.datatables.org/alltables.env"},"url":[{"execution-start-time":"0","execution-stop-time":"2","execution-time":"2","proxy":"DEFAULT","content":"http://datatables.org/alltables.env"},{"execution-start-time":"16","execution-stop-time":"17","execution-time":"1","proxy":"DEFAULT","content":"http://www.datatables.org/yahoo/finance/yahoo.finance.historicaldata.xml"},{"execution-start-time":"21","execution-stop-time":"30","execution-time":"9","proxy":"DEFAULT","content":"http://ichart.finance.yahoo.com/table.csv?g=d&f=2014&e=1&c=2013&b=1&a=0&d=0&s=EXR"},{"execution-start-time":"32","execution-stop-time":"39","execution-time":"7","proxy":"DEFAULT","content":"http://ichart.finance.yahoo.com/table.csv?g=d&f=2014&e=1&c=2013&b=1&a=0&d=0&s=EXR"}],"cache":[{"execution-start-time":"19","execution-stop-time":"19","execution-time":"0","method":"GET","type":"MEMCACHED","content":"15ff8982201f9901b491bc0b4de2c50d"},{"execution-start-time":"19","execution-stop-time":"19","execution-time":"0","method":"GET","type":"MEMCACHED","content":"128.83.130.4"},{"execution-start-time":"21","execution-stop-time":"21","execution-time":"0","method":"GET","type":"MEMCACHED","content":"baf8b0e80421a7416e068bf43db4ae96"},{"execution-start-time":"31","execution-stop-time":"31","execution-time":"0","method":"GET","type":"MEMCACHED","content":"4fc6d83a50062c04374f100cef2d9ad7"}],"query":[{"execution-start-time":"21","execution-stop-time":"31","execution-time":"10","params":"{url=[http://ichart.finance.yahoo.com/table.csv?g=d&f=2014&e=1&c=2013&b=1&a=0&d=0&s=EXR]}","content":"select * from csv(0,1) where url=@url"},{"execution-start-time":"31","execution-stop-time":"39","execution-time":"8","params":"{columnsNames=[Date,Open,High,Low,Close,Volume,Adj_Close], url=[http://ichart.finance.yahoo.com/table.csv?g=d&f=2014&e=1&c=2013&b=1&a=0&d=0&s=EXR]}","content":"select * from csv(2,0) where url=@url and columns=@columnsNames"}],"javascript":{"execution-time":"113","instructions-used":"3078306","table-name":"yahoo.finance.historicaldata"},"user-time":"132","service-time":"19","build-version":"36288"},"results":{"quote":[{"date":"2013-05-08","Date":"2013-05-08","Open":"44.19","High":"44.24","Low":"43.90","Close":"44.23","Volume":"651900","Adj_Close":"44.23"},{"date":"2013-05-07","Date":"2013-05-07","Open":"44.36","High":"44.42","Low":"44.14","Close":"44.19","Volume":"395700","Adj_Close":"44.19"},{"date":"2013-05-06","Date":"2013-05-06","Open":"44.15","High":"44.36","Low":"43.77","Close":"44.27","Volume":"455700","Adj_Close":"44.27"},{"date":"2013-05-03","Date":"2013-05-03","Open":"44.36","High":"44.45","Low":"43.99","Close":"44.07","Volume":"484300","Adj_Close":"44.07"},{"date":"2013-05-02","Date":"2013-05-02","Open":"43.65","High":"44.13","Low":"43.48","Close":"44.00","Volume":"661200","Adj_Close":"44.00"},{"date":"2013-05-01","Date":"2013-05-01","Open":"43.48","High":"43.96","Low":"43.32","Close":"43.48","Volume":"946600","Adj_Close":"43.48"},{"date":"2013-04-30","Date":"2013-04-30","Open":"42.85","High":"43.58","Low":"42.85","Close":"43.58","Volume":"1735000","Adj_Close":"43.58"},{"date":"2013-04-29","Date":"2013-04-29","Open":"42.77","High":"43.13","Low":"42.32","Close":"42.96","Volume":"673800","Adj_Close":"42.96"},{"date":"2013-04-26","Date":"2013-04-26","Open":"41.80","High":"42.23","Low":"41.74","Close":"41.99","Volume":"636400","Adj_Close":"41.99"},{"date":"2013-04-25","Date":"2013-04-25","Open":"41.99","High":"41.99","Low":"41.50","Close":"41.68","Volume":"736200","Adj_Close":"41.68"},{"date":"2013-04-24","Date":"2013-04-24","Open":"41.77","High":"41.95","Low":"41.49","Close":"41.86","Volume":"552500","Adj_Close":"41.86"},{"date":"2013-04-23","Date":"2013-04-23","Open":"41.60","High":"41.84","Low":"41.32","Close":"41.65","Volume":"545200","Adj_Close":"41.65"},{"date":"2013-04-22","Date":"2013-04-22","Open":"42.11","High":"42.11","Low":"41.45","Close":"41.52","Volume":"496600","Adj_Close":"41.52"},{"date":"2013-04-19","Date":"2013-04-19","Open":"41.34","High":"42.05","Low":"41.05","Close":"42.01","Volume":"610500","Adj_Close":"42.01"},{"date":"2013-04-18","Date":"2013-04-18","Open":"41.33","High":"41.38","Low":"40.98","Close":"41.22","Volume":"497100","Adj_Close":"41.22"},{"date":"2013-04-17","Date":"2013-04-17","Open":"41.35","High":"41.57","Low":"40.90","Close":"41.20","Volume":"869700","Adj_Close":"41.20"},{"date":"2013-04-16","Date":"2013-04-16","Open":"41.02","High":"41.72","Low":"40.66","Close":"41.70","Volume":"722000","Adj_Close":"41.70"},{"date":"2013-04-15","Date":"2013-04-15","Open":"41.25","High":"41.50","Low":"40.81","Close":"40.88","Volume":"1073100","Adj_Close":"40.88"},{"date":"2013-04-12","Date":"2013-04-12","Open":"41.33","High":"41.57","Low":"41.27","Close":"41.54","Volume":"570700","Adj_Close":"41.54"},{"date":"2013-04-11","Date":"2013-04-11","Open":"41.08","High":"41.69","Low":"41.02","Close":"41.49","Volume":"919400","Adj_Close":"41.49"},{"date":"2013-04-10","Date":"2013-04-10","Open":"40.54","High":"41.15","Low":"40.46","Close":"41.09","Volume":"1153600","Adj_Close":"41.09"},{"date":"2013-04-09","Date":"2013-04-09","Open":"40.24","High":"40.68","Low":"40.01","Close":"40.53","Volume":"831000","Adj_Close":"40.53"},{"date":"2013-04-08","Date":"2013-04-08","Open":"39.83","High":"40.24","Low":"39.56","Close":"40.12","Volume":"517800","Adj_Close":"40.12"},{"date":"2013-04-05","Date":"2013-04-05","Open":"39.17","High":"39.76","Low":"39.01","Close":"39.75","Volume":"352600","Adj_Close":"39.75"},{"date":"2013-04-04","Date":"2013-04-04","Open":"39.28","High":"39.51","Low":"39.13","Close":"39.49","Volume":"365900","Adj_Close":"39.49"},{"date":"2013-04-03","Date":"2013-04-03","Open":"39.65","High":"39.74","Low":"39.05","Close":"39.19","Volume":"661600","Adj_Close":"39.19"},{"date":"2013-04-02","Date":"2013-04-02","Open":"39.57","High":"39.86","Low":"39.42","Close":"39.61","Volume":"496300","Adj_Close":"39.61"},{"date":"2013-04-01","Date":"2013-04-01","Open":"39.24","High":"39.44","Low":"38.87","Close":"39.44","Volume":"558600","Adj_Close":"39.44"},{"date":"2013-03-28","Date":"2013-03-28","Open":"39.46","High":"39.61","Low":"39.19","Close":"39.27","Volume":"1021900","Adj_Close":"39.27"},{"date":"2013-03-27","Date":"2013-03-27","Open":"39.26","High":"39.39","Low":"39.01","Close":"39.39","Volume":"483300","Adj_Close":"39.39"},{"date":"2013-03-26","Date":"2013-03-26","Open":"39.24","High":"39.53","Low":"39.20","Close":"39.49","Volume":"706200","Adj_Close":"39.49"},{"date":"2013-03-25","Date":"2013-03-25","Open":"39.16","High":"39.45","Low":"38.83","Close":"39.14","Volume":"957400","Adj_Close":"39.14"},{"date":"2013-03-22","Date":"2013-03-22","Open":"38.43","High":"39.09","Low":"38.31","Close":"39.09","Volume":"596200","Adj_Close":"39.09"},{"date":"2013-03-21","Date":"2013-03-21","Open":"38.53","High":"39.03","Low":"38.42","Close":"38.42","Volume":"673300","Adj_Close":"38.42"},{"date":"2013-03-20","Date":"2013-03-20","Open":"38.38","High":"38.66","Low":"38.24","Close":"38.64","Volume":"448000","Adj_Close":"38.64"},{"date":"2013-03-19","Date":"2013-03-19","Open":"38.47","High":"38.57","Low":"37.97","Close":"38.21","Volume":"618000","Adj_Close":"38.21"},{"date":"2013-03-18","Date":"2013-03-18","Open":"38.00","High":"38.41","Low":"37.88","Close":"38.41","Volume":"629300","Adj_Close":"38.41"},{"date":"2013-03-15","Date":"2013-03-15","Open":"38.15","High":"38.20","Low":"37.83","Close":"38.13","Volume":"1235200","Adj_Close":"38.13"},{"date":"2013-03-14","Date":"2013-03-14","Open":"38.06","High":"38.41","Low":"37.88","Close":"38.12","Volume":"1068300","Adj_Close":"38.12"},{"date":"2013-03-13","Date":"2013-03-13","Open":"38.79","High":"39.42","Low":"38.09","Close":"38.12","Volume":"991200","Adj_Close":"38.12"},{"date":"2013-03-12","Date":"2013-03-12","Open":"38.73","High":"39.07","Low":"38.67","Close":"38.91","Volume":"629200","Adj_Close":"38.66"},{"date":"2013-03-11","Date":"2013-03-11","Open":"39.16","High":"39.16","Low":"38.54","Close":"38.86","Volume":"572300","Adj_Close":"38.61"},{"date":"2013-03-08","Date":"2013-03-08","Open":"39.13","High":"39.23","Low":"38.77","Close":"39.21","Volume":"880600","Adj_Close":"38.96"},{"date":"2013-03-07","Date":"2013-03-07","Open":"39.18","High":"39.50","Low":"38.93","Close":"39.03","Volume":"736300","Adj_Close":"38.78"},{"date":"2013-03-06","Date":"2013-03-06","Open":"39.59","High":"39.60","Low":"39.08","Close":"39.17","Volume":"816800","Adj_Close":"38.92"},{"date":"2013-03-05","Date":"2013-03-05","Open":"38.55","High":"39.46","Low":"38.48","Close":"39.46","Volume":"995900","Adj_Close":"39.21"},{"date":"2013-03-04","Date":"2013-03-04","Open":"37.54","High":"38.51","Low":"37.53","Close":"38.44","Volume":"860400","Adj_Close":"38.19"},{"date":"2013-03-01","Date":"2013-03-01","Open":"37.39","High":"37.62","Low":"36.89","Close":"37.52","Volume":"1055000","Adj_Close":"37.28"},{"date":"2013-02-28","Date":"2013-02-28","Open":"37.56","High":"37.77","Low":"37.41","Close":"37.44","Volume":"1291000","Adj_Close":"37.20"},{"date":"2013-02-27","Date":"2013-02-27","Open":"37.28","High":"37.58","Low":"37.14","Close":"37.53","Volume":"544300","Adj_Close":"37.29"},{"date":"2013-02-26","Date":"2013-02-26","Open":"37.18","High":"37.31","Low":"36.50","Close":"37.29","Volume":"1996200","Adj_Close":"37.05"},{"date":"2013-02-25","Date":"2013-02-25","Open":"38.40","High":"38.49","Low":"37.14","Close":"37.19","Volume":"1092000","Adj_Close":"36.95"},{"date":"2013-02-22","Date":"2013-02-22","Open":"37.80","High":"38.28","Low":"37.40","Close":"38.12","Volume":"833800","Adj_Close":"37.88"},{"date":"2013-02-21","Date":"2013-02-21","Open":"38.27","High":"38.31","Low":"37.56","Close":"37.82","Volume":"1372200","Adj_Close":"37.58"},{"date":"2013-02-20","Date":"2013-02-20","Open":"38.49","High":"38.84","Low":"38.37","Close":"38.40","Volume":"945000","Adj_Close":"38.15"},{"date":"2013-02-19","Date":"2013-02-19","Open":"38.57","High":"38.82","Low":"38.06","Close":"38.50","Volume":"1403600","Adj_Close":"38.25"},{"date":"2013-02-15","Date":"2013-02-15","Open":"39.16","High":"39.33","Low":"37.95","Close":"38.70","Volume":"2269000","Adj_Close":"38.45"},{"date":"2013-02-14","Date":"2013-02-14","Open":"40.04","High":"40.04","Low":"39.53","Close":"39.54","Volume":"1268800","Adj_Close":"39.29"},{"date":"2013-02-13","Date":"2013-02-13","Open":"40.49","High":"40.66","Low":"39.87","Close":"40.06","Volume":"756400","Adj_Close":"39.80"},{"date":"2013-02-12","Date":"2013-02-12","Open":"40.48","High":"40.61","Low":"40.32","Close":"40.35","Volume":"508000","Adj_Close":"40.09"},{"date":"2013-02-11","Date":"2013-02-11","Open":"40.35","High":"40.74","Low":"40.35","Close":"40.41","Volume":"463400","Adj_Close":"40.15"},{"date":"2013-02-08","Date":"2013-02-08","Open":"40.06","High":"40.28","Low":"39.85","Close":"40.28","Volume":"536500","Adj_Close":"40.02"},{"date":"2013-02-07","Date":"2013-02-07","Open":"40.34","High":"40.41","Low":"39.92","Close":"39.97","Volume":"567800","Adj_Close":"39.71"},{"date":"2013-02-06","Date":"2013-02-06","Open":"40.25","High":"40.36","Low":"39.96","Close":"40.16","Volume":"829200","Adj_Close":"39.90"},{"date":"2013-02-05","Date":"2013-02-05","Open":"40.63","High":"40.97","Low":"40.13","Close":"40.15","Volume":"1049300","Adj_Close":"39.89"},{"date":"2013-02-04","Date":"2013-02-04","Open":"40.36","High":"40.59","Low":"40.19","Close":"40.40","Volume":"876800","Adj_Close":"40.14"},{"date":"2013-02-01","Date":"2013-02-01","Open":"39.96","High":"40.50","Low":"39.80","Close":"40.40","Volume":"834000","Adj_Close":"40.14"},{"date":"2013-01-31","Date":"2013-01-31","Open":"39.57","High":"39.88","Low":"39.49","Close":"39.84","Volume":"1092600","Adj_Close":"39.58"},{"date":"2013-01-30","Date":"2013-01-30","Open":"39.64","High":"39.75","Low":"39.42","Close":"39.60","Volume":"1032400","Adj_Close":"39.35"},{"date":"2013-01-29","Date":"2013-01-29","Open":"39.26","High":"40.05","Low":"39.21","Close":"39.65","Volume":"14499900","Adj_Close":"39.40"},{"date":"2013-01-28","Date":"2013-01-28","Open":"39.21","High":"39.40","Low":"39.00","Close":"39.19","Volume":"501200","Adj_Close":"38.94"},{"date":"2013-01-25","Date":"2013-01-25","Open":"39.07","High":"39.33","Low":"38.83","Close":"39.32","Volume":"622600","Adj_Close":"39.07"},{"date":"2013-01-24","Date":"2013-01-24","Open":"38.58","High":"39.57","Low":"38.46","Close":"38.95","Volume":"1261300","Adj_Close":"38.70"},{"date":"2013-01-23","Date":"2013-01-23","Open":"38.63","High":"38.72","Low":"38.33","Close":"38.41","Volume":"305000","Adj_Close":"38.16"},{"date":"2013-01-22","Date":"2013-01-22","Open":"38.45","High":"38.63","Low":"38.31","Close":"38.58","Volume":"521600","Adj_Close":"38.33"},{"date":"2013-01-18","Date":"2013-01-18","Open":"38.36","High":"38.53","Low":"38.07","Close":"38.53","Volume":"425500","Adj_Close":"38.28"},{"date":"2013-01-17","Date":"2013-01-17","Open":"38.15","High":"38.51","Low":"38.11","Close":"38.17","Volume":"442200","Adj_Close":"37.92"},{"date":"2013-01-16","Date":"2013-01-16","Open":"37.90","High":"37.99","Low":"37.68","Close":"37.92","Volume":"538900","Adj_Close":"37.68"},{"date":"2013-01-15","Date":"2013-01-15","Open":"37.64","High":"37.75","Low":"37.57","Close":"37.71","Volume":"545300","Adj_Close":"37.47"},{"date":"2013-01-14","Date":"2013-01-14","Open":"37.60","High":"37.67","Low":"37.55","Close":"37.64","Volume":"278700","Adj_Close":"37.40"},{"date":"2013-01-11","Date":"2013-01-11","Open":"37.81","High":"37.82","Low":"37.45","Close":"37.64","Volume":"600100","Adj_Close":"37.40"},{"date":"2013-01-10","Date":"2013-01-10","Open":"37.87","High":"37.97","Low":"37.70","Close":"37.80","Volume":"555000","Adj_Close":"37.56"},{"date":"2013-01-09","Date":"2013-01-09","Open":"37.29","High":"37.81","Low":"37.12","Close":"37.81","Volume":"596000","Adj_Close":"37.57"},{"date":"2013-01-08","Date":"2013-01-08","Open":"37.31","High":"37.45","Low":"37.00","Close":"37.15","Volume":"446700","Adj_Close":"36.91"},{"date":"2013-01-07","Date":"2013-01-07","Open":"36.95","High":"37.60","Low":"36.95","Close":"37.40","Volume":"590600","Adj_Close":"37.16"},{"date":"2013-01-04","Date":"2013-01-04","Open":"37.15","High":"37.36","Low":"36.96","Close":"37.33","Volume":"459100","Adj_Close":"37.09"},{"date":"2013-01-03","Date":"2013-01-03","Open":"36.88","High":"37.42","Low":"36.88","Close":"37.15","Volume":"680500","Adj_Close":"36.91"},{"date":"2013-01-02","Date":"2013-01-02","Open":"36.81","High":"37.14","Low":"36.64","Close":"36.85","Volume":"486400","Adj_Close":"36.61"}]}}}